[
null,
{"animationId":-1,"damage":{"critical":true,"elementId":-1,"formula":"a.atk * 4 - b.def * 2","type":1,"variance":20},"description":"","effects":[{"code":21,"dataId":0,"value1":1,"value2":0}],"hitType":1,"iconIndex":76,"id":1,"message1":"發起攻擊！","message2":"","mpCost":0,"name":"","note":"スキル１番は［攻撃］コマンドを\n選択したときに使用されます。","occasion":1,"repeats":1,"requiredWtypeId1":0,"requiredWtypeId2":0,"scope":1,"speed":0,"stypeId":0,"successRate":100,"tpCost":0,"tpGain":10},
{"animationId":0,"damage":{"critical":false,"elementId":0,"formula":"0","type":0,"variance":20},"description":"","effects":[{"code":21,"dataId":2,"value1":1,"value2":0}],"hitType":0,"iconIndex":81,"id":2,"message1":"進行著防禦。","message2":"","mpCost":0,"name":"防禦","note":"スキル２番は［防禦］コマンドを\n選択したときに使用されます。","occasion":1,"repeats":1,"requiredWtypeId1":0,"requiredWtypeId2":0,"scope":11,"speed":2000,"stypeId":0,"successRate":100,"tpCost":0,"tpGain":10},
{"animationId":-1,"damage":{"critical":true,"elementId":-1,"formula":"a.atk * 4 - b.def * 2","type":1,"variance":20},"description":"","effects":[],"hitType":1,"iconIndex":76,"id":3,"message1":"發起攻擊！","message2":"","mpCost":0,"name":"連續攻撃","note":"","occasion":1,"repeats":2,"requiredWtypeId1":0,"requiredWtypeId2":0,"scope":1,"speed":0,"stypeId":0,"successRate":100,"tpCost":0,"tpGain":5},
{"animationId":-1,"damage":{"critical":true,"elementId":-1,"formula":"a.atk * 4 - b.def * 2","type":1,"variance":20},"description":"","effects":[{"code":21,"dataId":0,"value1":1,"value2":0}],"hitType":1,"iconIndex":76,"id":4,"message1":"發起攻擊！","message2":"","mpCost":0,"name":"２次攻擊","note":"","occasion":1,"repeats":1,"requiredWtypeId1":0,"requiredWtypeId2":0,"scope":4,"speed":0,"stypeId":0,"successRate":100,"tpCost":0,"tpGain":5},
{"animationId":-1,"damage":{"critical":true,"elementId":-1,"formula":"a.atk * 4 - b.def * 2","type":1,"variance":20},"description":"","effects":[{"code":21,"dataId":0,"value1":1,"value2":0}],"hitType":1,"iconIndex":76,"id":5,"message1":"發起攻擊！","message2":"","mpCost":0,"name":"３次攻擊","note":"","occasion":1,"repeats":1,"requiredWtypeId1":0,"requiredWtypeId2":0,"scope":5,"speed":0,"stypeId":0,"successRate":100,"tpCost":0,"tpGain":4},
{"animationId":0,"damage":{"critical":false,"elementId":0,"formula":"0","type":0,"variance":20},"description":"","effects":[{"code":41,"dataId":0,"value1":0,"value2":0}],"hitType":0,"iconIndex":82,"id":6,"message1":"逃跑了。","message2":"","mpCost":0,"name":"逃跑","note":"","occasion":1,"repeats":1,"requiredWtypeId1":0,"requiredWtypeId2":0,"scope":11,"speed":0,"stypeId":0,"successRate":100,"tpCost":0,"tpGain":0},
{"animationId":0,"damage":{"critical":false,"elementId":0,"formula":"0","type":0,"variance":20},"description":"","effects":[],"hitType":0,"iconIndex":81,"id":7,"message1":"在觀察情況。","message2":"","mpCost":0,"name":"觀察情況","note":"","occasion":1,"repeats":1,"requiredWtypeId1":0,"requiredWtypeId2":0,"scope":0,"speed":0,"stypeId":0,"successRate":100,"tpCost":0,"tpGain":10},
{"animationId":41,"damage":{"critical":false,"elementId":0,"formula":"3","type":3,"variance":20},"description":"回復體力的魔法。\n精靈能用這個是當然的喲！","effects":[],"hitType":0,"iconIndex":72,"id":8,"message1":"詠唱了%1！","message2":"不要緊嗎！？我幫你進行回復！","mpCost":2,"name":"治癒","note":"","occasion":0,"repeats":1,"requiredWtypeId1":0,"requiredWtypeId2":0,"scope":7,"speed":0,"stypeId":1,"successRate":100,"tpCost":0,"tpGain":10},
{"animationId":66,"damage":{"critical":false,"elementId":2,"formula":"100 + a.mat * 2 - b.mdf * 2","type":1,"variance":20},"description":"","effects":[],"hitType":2,"iconIndex":64,"id":9,"message1":"詠唱了%1！","message2":"","mpCost":5,"name":"火焰","note":"","occasion":1,"repeats":1,"requiredWtypeId1":0,"requiredWtypeId2":0,"scope":1,"speed":0,"stypeId":1,"successRate":100,"tpCost":0,"tpGain":10},
{"animationId":78,"damage":{"critical":false,"elementId":4,"formula":"100 + a.mat * 2 - b.mdf * 2","type":1,"variance":20},"description":"","effects":[],"hitType":2,"iconIndex":66,"id":10,"message1":"詠唱了%1！","message2":"","mpCost":5,"name":"閃光","note":"","occasion":1,"repeats":1,"requiredWtypeId1":0,"requiredWtypeId2":0,"scope":2,"speed":0,"stypeId":1,"successRate":100,"tpCost":0,"tpGain":10},
{"animationId":0,"damage":{"critical":false,"elementId":0,"formula":"0","type":0,"variance":20},"description":"","effects":[{"code":44,"dataId":4,"value1":1,"value2":0}],"hitType":0,"iconIndex":84,"id":11,"message1":"","message2":"","mpCost":0,"name":"性騷擾","note":"","occasion":2,"repeats":1,"requiredWtypeId1":0,"requiredWtypeId2":0,"scope":0,"speed":0,"stypeId":1,"successRate":100,"tpCost":0,"tpGain":0},
{"animationId":0,"damage":{"critical":false,"elementId":0,"formula":"0","type":0,"variance":20},"description":"和海坂牽手。\n千里之行始於足下。","effects":[{"code":44,"dataId":12,"value1":1,"value2":0}],"hitType":0,"iconIndex":84,"id":12,"message1":"","message2":"","mpCost":0,"name":"牽手","note":"","occasion":2,"repeats":1,"requiredWtypeId1":0,"requiredWtypeId2":0,"scope":0,"speed":0,"stypeId":1,"successRate":100,"tpCost":0,"tpGain":0},
{"animationId":0,"damage":{"critical":false,"elementId":0,"formula":"0","type":0,"variance":20},"description":"在她毛茸茸的耳邊輕語。\n那裡好像意外地很敏感。","effects":[{"code":44,"dataId":42,"value1":1,"value2":0}],"hitType":0,"iconIndex":84,"id":13,"message1":"","message2":"","mpCost":0,"name":"说下流的話","note":"","occasion":2,"repeats":1,"requiredWtypeId1":0,"requiredWtypeId2":0,"scope":1,"speed":0,"stypeId":1,"successRate":100,"tpCost":0,"tpGain":0},
{"animationId":0,"damage":{"critical":false,"elementId":0,"formula":"0","type":0,"variance":20},"description":"性騷擾的基礎也是必修課。\n為此，想要窮極它的奧妙需要堵上人生。","effects":[{"code":44,"dataId":43,"value1":1,"value2":0}],"hitType":0,"iconIndex":84,"id":14,"message1":"","message2":"","mpCost":0,"name":"揉屁股","note":"","occasion":2,"repeats":1,"requiredWtypeId1":0,"requiredWtypeId2":0,"scope":1,"speed":0,"stypeId":1,"successRate":100,"tpCost":0,"tpGain":0},
{"animationId":0,"damage":{"critical":false,"elementId":0,"formula":"0","type":0,"variance":20},"description":"兔子的耳朵上有神經，\n巴拉巴拉巴拉巴拉，總之是敏感帶。","effects":[{"code":44,"dataId":44,"value1":1,"value2":0}],"hitType":0,"iconIndex":7,"id":15,"message1":"","message2":"","mpCost":0,"name":"摸耳朵","note":"","occasion":2,"repeats":1,"requiredWtypeId1":0,"requiredWtypeId2":0,"scope":1,"speed":0,"stypeId":1,"successRate":100,"tpCost":0,"tpGain":0},
{"animationId":0,"damage":{"critical":false,"elementId":0,"formula":"0","type":0,"variance":20},"description":"誇誇她她就會做的更好。\n多多地摸她吧。","effects":[{"code":44,"dataId":16,"value1":1,"value2":0}],"hitType":0,"iconIndex":84,"id":16,"message1":"","message2":"","mpCost":0,"name":"摸摸頭","note":"","occasion":2,"repeats":1,"requiredWtypeId1":0,"requiredWtypeId2":0,"scope":1,"speed":0,"stypeId":1,"successRate":100,"tpCost":0,"tpGain":0},
{"animationId":0,"damage":{"critical":false,"elementId":0,"formula":"0","type":0,"variance":20},"description":"讓她把裙子掀起來。\n看著擼也是一種浪漫。","effects":[{"code":44,"dataId":46,"value1":1,"value2":0}],"hitType":0,"iconIndex":84,"id":17,"message1":"","message2":"","mpCost":0,"name":"讓她掀起裙子","note":"","occasion":2,"repeats":1,"requiredWtypeId1":0,"requiredWtypeId2":0,"scope":1,"speed":0,"stypeId":1,"successRate":100,"tpCost":0,"tpGain":0},
{"animationId":0,"damage":{"critical":false,"elementId":0,"formula":"0","type":0,"variance":20},"description":"Go! Figjt! Win!","effects":[{"code":44,"dataId":21,"value1":1,"value2":0}],"hitType":0,"iconIndex":87,"id":18,"message1":"","message2":"","mpCost":0,"name":"換上啦啦隊服","note":"","occasion":2,"repeats":1,"requiredWtypeId1":0,"requiredWtypeId2":0,"scope":1,"speed":0,"stypeId":1,"successRate":100,"tpCost":0,"tpGain":0},
{"animationId":0,"damage":{"critical":false,"elementId":0,"formula":"0","type":0,"variance":20},"description":"海坂平時的衣服。\n粉色就是精靈的證明！","effects":[{"code":44,"dataId":22,"value1":1,"value2":0}],"hitType":0,"iconIndex":89,"id":19,"message1":"","message2":"","mpCost":0,"name":"換上普通衣服","note":"","occasion":2,"repeats":1,"requiredWtypeId1":0,"requiredWtypeId2":0,"scope":1,"speed":0,"stypeId":1,"successRate":100,"tpCost":0,"tpGain":0},
{"animationId":0,"damage":{"critical":false,"elementId":0,"formula":"0","type":0,"variance":20},"description":"咩—咩—咩—咩—。咩—？\n咩—咩—咩—。咩———。","effects":[{"code":44,"dataId":33,"value1":1,"value2":0}],"hitType":0,"iconIndex":88,"id":20,"message1":"","message2":"","mpCost":0,"name":"換上小羊服","note":"","occasion":2,"repeats":1,"requiredWtypeId1":0,"requiredWtypeId2":0,"scope":1,"speed":0,"stypeId":1,"successRate":100,"tpCost":0,"tpGain":0},
{"animationId":0,"damage":{"critical":false,"elementId":0,"formula":"0","type":0,"variance":20},"description":"跳舞到天亮吧！\n你擅長肚皮舞嗎？","effects":[{"code":44,"dataId":34,"value1":1,"value2":0}],"hitType":0,"iconIndex":88,"id":21,"message1":"","message2":"","mpCost":0,"name":"換上舞女服","note":"","occasion":2,"repeats":1,"requiredWtypeId1":0,"requiredWtypeId2":0,"scope":1,"speed":0,"stypeId":1,"successRate":100,"tpCost":0,"tpGain":0},
{"animationId":0,"damage":{"critical":false,"elementId":0,"formula":"0","type":0,"variance":20},"description":"我發誓不論健康或是疾病、\n都會陪伴在你身邊。","effects":[{"code":44,"dataId":35,"value1":1,"value2":0}],"hitType":0,"iconIndex":87,"id":22,"message1":"","message2":"","mpCost":0,"name":"換上婚紗","note":"","occasion":2,"repeats":1,"requiredWtypeId1":0,"requiredWtypeId2":0,"scope":1,"speed":0,"stypeId":1,"successRate":100,"tpCost":0,"tpGain":0},
{"animationId":0,"damage":{"critical":false,"elementId":0,"formula":"0","type":0,"variance":20},"description":"相當女孩的護花使者首先要這樣。\n書和電視上基本都是這樣說的。","effects":[{"code":44,"dataId":45,"value1":1,"value2":0}],"hitType":0,"iconIndex":84,"id":23,"message1":"","message2":"","mpCost":0,"name":"稱讚她的衣服","note":"","occasion":2,"repeats":1,"requiredWtypeId1":0,"requiredWtypeId2":0,"scope":1,"speed":0,"stypeId":1,"successRate":100,"tpCost":0,"tpGain":0},
{"animationId":0,"damage":{"critical":false,"elementId":0,"formula":"0","type":0,"variance":20},"description":"使人成為神之手的基礎技能。\n手的形狀各色各樣，但外行還是別上手比較好。","effects":[{"code":44,"dataId":47,"value1":1,"value2":0}],"hitType":0,"iconIndex":84,"id":24,"message1":"","message2":"","mpCost":0,"name":"愛撫","note":"","occasion":2,"repeats":1,"requiredWtypeId1":0,"requiredWtypeId2":0,"scope":1,"speed":0,"stypeId":1,"successRate":100,"tpCost":0,"tpGain":0},
{"animationId":0,"damage":{"critical":false,"elementId":0,"formula":"0","type":0,"variance":20},"description":"讓某人縮小，以便戰鬥！\n哎？還能用作性騷擾？怎麼可能……。","effects":[{"code":44,"dataId":86,"value1":1,"value2":0}],"hitType":0,"iconIndex":84,"id":25,"message1":"","message2":"","mpCost":0,"name":"縮小術","note":"","occasion":2,"repeats":1,"requiredWtypeId1":0,"requiredWtypeId2":0,"scope":1,"speed":0,"stypeId":1,"successRate":100,"tpCost":0,"tpGain":0},
{"animationId":0,"damage":{"critical":false,"elementId":0,"formula":"0","type":0,"variance":20},"description":"你還在因沒有幸運色狼事件而煩悶嗎！\n命運不是要靠自己掌控嘛。去創造命運吧！","effects":[{"code":44,"dataId":17,"value1":1,"value2":0}],"hitType":0,"iconIndex":84,"id":26,"message1":"","message2":"","mpCost":0,"name":"意外摟抱","note":"","occasion":2,"repeats":1,"requiredWtypeId1":0,"requiredWtypeId2":0,"scope":1,"speed":0,"stypeId":1,"successRate":100,"tpCost":0,"tpGain":0},
{"animationId":0,"damage":{"critical":false,"elementId":0,"formula":"0","type":0,"variance":20},"description":"法國料理也說是一開始要看著來享受。\n看也是一種出色的性騷擾哦。","effects":[{"code":44,"dataId":18,"value1":1,"value2":0}],"hitType":0,"iconIndex":84,"id":27,"message1":"","message2":"","mpCost":0,"name":"視姦","note":"","occasion":2,"repeats":1,"requiredWtypeId1":0,"requiredWtypeId2":0,"scope":1,"speed":0,"stypeId":1,"successRate":100,"tpCost":0,"tpGain":0},
{"animationId":0,"damage":{"critical":false,"elementId":0,"formula":"0","type":0,"variance":20},"description":"近似於前戲的性騷擾。\n想要窮極此路需要花費數十年的時間。","effects":[{"code":44,"dataId":52,"value1":1,"value2":0}],"hitType":0,"iconIndex":84,"id":28,"message1":"","message2":"","mpCost":0,"name":"揉胸","note":"","occasion":2,"repeats":1,"requiredWtypeId1":0,"requiredWtypeId2":0,"scope":1,"speed":0,"stypeId":1,"successRate":100,"tpCost":0,"tpGain":0},
{"animationId":0,"damage":{"critical":false,"elementId":0,"formula":"0","type":0,"variance":20},"description":"強行讓你愛的女孩摸性器。\n変態度提升了一級呢。","effects":[{"code":44,"dataId":54,"value1":1,"value2":0}],"hitType":0,"iconIndex":7,"id":29,"message1":"","message2":"","mpCost":0,"name":"讓她摸胯下","note":"","occasion":2,"repeats":1,"requiredWtypeId1":0,"requiredWtypeId2":0,"scope":1,"speed":0,"stypeId":1,"successRate":100,"tpCost":0,"tpGain":0},
{"animationId":0,"damage":{"critical":false,"elementId":0,"formula":"a.atk","type":1,"variance":20},"description":"","effects":[],"hitType":0,"iconIndex":77,"id":30,"message1":"魔物釋放了%1！","message2":"『－－－\"#$%&'()0&0&'()BHI'O'G)%&'(%$F&'(GBP)H　』","mpCost":0,"name":"【＄％T&'%'&%'('(】","note":"","occasion":0,"repeats":1,"requiredWtypeId1":0,"requiredWtypeId2":0,"scope":2,"speed":12,"stypeId":2,"successRate":100,"tpCost":0,"tpGain":0},
{"animationId":0,"damage":{"critical":false,"elementId":0,"formula":"0","type":0,"variance":20},"description":"告知對方自己壓抑著的慾望。\n觀察對方反應的意識流性騷擾。","effects":[{"code":44,"dataId":56,"value1":1,"value2":0}],"hitType":0,"iconIndex":84,"id":31,"message1":"","message2":"","mpCost":0,"name":"傾訴慾望","note":"","occasion":2,"repeats":1,"requiredWtypeId1":0,"requiredWtypeId2":0,"scope":1,"speed":0,"stypeId":1,"successRate":100,"tpCost":0,"tpGain":0},
{"animationId":0,"damage":{"critical":false,"elementId":0,"formula":"0","type":0,"variance":20},"description":"最強性騷擾之一。\n靠射得多少來展現男人的魅力吧（固定服裝）。","effects":[{"code":44,"dataId":57,"value1":1,"value2":0}],"hitType":0,"iconIndex":7,"id":32,"message1":"","message2":"","mpCost":0,"name":"精液噴灑","note":"","occasion":2,"repeats":1,"requiredWtypeId1":0,"requiredWtypeId2":0,"scope":1,"speed":0,"stypeId":1,"successRate":100,"tpCost":0,"tpGain":0},
{"animationId":0,"damage":{"critical":false,"elementId":0,"formula":"0","type":0,"variance":20},"description":"傳達愛意的動作。\n將心意傾注於其中吧。","effects":[{"code":44,"dataId":58,"value1":1,"value2":0}],"hitType":0,"iconIndex":7,"id":33,"message1":"","message2":"","mpCost":0,"name":"接吻","note":"","occasion":2,"repeats":1,"requiredWtypeId1":0,"requiredWtypeId2":0,"scope":1,"speed":0,"stypeId":1,"successRate":100,"tpCost":0,"tpGain":0},
{"animationId":0,"damage":{"critical":false,"elementId":0,"formula":"0","type":0,"variance":20},"description":"思考海坂是怎樣看自己的。\n客觀的視線對性騷擾而言是必須的。","effects":[{"code":44,"dataId":15,"value1":1,"value2":0}],"hitType":0,"iconIndex":4,"id":34,"message1":"","message2":"","mpCost":0,"name":"確認好感度","note":"","occasion":2,"repeats":1,"requiredWtypeId1":0,"requiredWtypeId2":0,"scope":1,"speed":0,"stypeId":1,"successRate":100,"tpCost":0,"tpGain":0},
{"animationId":0,"damage":{"critical":false,"elementId":0,"formula":"2","type":1,"variance":20},"description":"","effects":[],"hitType":0,"iconIndex":0,"id":35,"message1":"釋放了%1！","message2":"","mpCost":0,"name":"攻撃","note":"","occasion":0,"repeats":1,"requiredWtypeId1":0,"requiredWtypeId2":0,"scope":1,"speed":0,"stypeId":1,"successRate":75,"tpCost":0,"tpGain":0},
{"animationId":0,"damage":{"critical":false,"elementId":0,"formula":"0","type":0,"variance":20},"description":"","effects":[],"hitType":0,"iconIndex":0,"id":36,"message1":"","message2":"古菈布菈握著拳頭！","mpCost":0,"name":"古菈布菈戰鬥中","note":"","occasion":0,"repeats":1,"requiredWtypeId1":0,"requiredWtypeId2":0,"scope":0,"speed":0,"stypeId":0,"successRate":100,"tpCost":0,"tpGain":0},
{"animationId":0,"damage":{"critical":false,"elementId":0,"formula":"3000","type":3,"variance":20},"description":"從遙遠的地方傳來的祈禱之力。\n你，有著獲得幸福的權利。","effects":[],"hitType":0,"iconIndex":72,"id":37,"message1":"詠唱了%1！","message2":"【海坂】「我們、不會輸的！」","mpCost":1000,"name":"超級治癒","note":"","occasion":0,"repeats":1,"requiredWtypeId1":0,"requiredWtypeId2":0,"scope":8,"speed":0,"stypeId":1,"successRate":100,"tpCost":0,"tpGain":0},
{"animationId":0,"damage":{"critical":false,"elementId":0,"formula":"9999","type":3,"variance":20},"description":"淨化一切痛苦的魔法。\n不論倒下多少次都不放棄。","effects":[{"code":44,"dataId":104,"value1":1,"value2":0}],"hitType":0,"iconIndex":72,"id":38,"message1":"詠唱了%1！","message2":"【海坂】「還沒完呢！還不能放棄！」","mpCost":2000,"name":"終極治癒","note":"","occasion":0,"repeats":1,"requiredWtypeId1":0,"requiredWtypeId2":0,"scope":8,"speed":0,"stypeId":1,"successRate":100,"tpCost":0,"tpGain":0},
{"animationId":0,"damage":{"critical":false,"elementId":0,"formula":"0","type":0,"variance":20},"description":"","effects":[],"hitType":0,"iconIndex":0,"id":39,"message1":"","message2":"","mpCost":0,"name":"","note":"","occasion":0,"repeats":1,"requiredWtypeId1":0,"requiredWtypeId2":0,"scope":1,"speed":0,"stypeId":1,"successRate":100,"tpCost":0,"tpGain":0},
{"animationId":0,"damage":{"critical":false,"elementId":0,"formula":"0","type":0,"variance":20},"description":"","effects":[],"hitType":0,"iconIndex":0,"id":40,"message1":"","message2":"","mpCost":0,"name":"","note":"","occasion":0,"repeats":1,"requiredWtypeId1":0,"requiredWtypeId2":0,"scope":1,"speed":0,"stypeId":1,"successRate":100,"tpCost":0,"tpGain":0},
{"animationId":22,"damage":{"critical":false,"elementId":0,"formula":"4","type":1,"variance":20},"description":"模仿如今已經不存在了的動物的動作，\n以看不見的速度不斷進攻。","effects":[],"hitType":0,"iconIndex":64,"id":41,"message1":"釋放了%1！","message2":"【古菈布菈】「飛散吧。——！」","mpCost":4,"name":"演舞・幻獸之型","note":"","occasion":0,"repeats":1,"requiredWtypeId1":0,"requiredWtypeId2":0,"scope":2,"speed":5,"stypeId":1,"successRate":100,"tpCost":0,"tpGain":0},
{"animationId":44,"damage":{"critical":false,"elementId":0,"formula":"5","type":3,"variance":20},"description":"跳起美麗的舞蹈，讓夥伴們回復。","effects":[],"hitType":0,"iconIndex":72,"id":42,"message1":"釋放了%1！","message2":"【古菈布菈】「稍微休息下吧！」","mpCost":3,"name":"演舞・爽風之型","note":"","occasion":0,"repeats":1,"requiredWtypeId1":0,"requiredWtypeId2":0,"scope":8,"speed":0,"stypeId":1,"successRate":100,"tpCost":0,"tpGain":0},
{"animationId":26,"damage":{"critical":false,"elementId":0,"formula":"10","type":1,"variance":20},"description":"極力將力量傾注於拳頭，\n用力學上最具效率的動作發出毆打。","effects":[],"hitType":0,"iconIndex":77,"id":43,"message1":"詠唱了%1！","message2":"【古菈布菈】「吃我這一招吧！」","mpCost":3,"name":"演舞・牙爪之型","note":"","occasion":0,"repeats":1,"requiredWtypeId1":0,"requiredWtypeId2":0,"scope":1,"speed":0,"stypeId":1,"successRate":100,"tpCost":0,"tpGain":0},
{"animationId":36,"damage":{"critical":false,"elementId":0,"formula":"0","type":0,"variance":20},"description":"湧起氣，提升全隊的士氣。","effects":[{"code":31,"dataId":2,"value1":5,"value2":0}],"hitType":0,"iconIndex":73,"id":44,"message1":"釋放了%1！","message2":"【古菈布菈】「接下來才是我的全部實力！」","mpCost":2,"name":"演舞・黃金之型","note":"","occasion":0,"repeats":1,"requiredWtypeId1":0,"requiredWtypeId2":0,"scope":8,"speed":0,"stypeId":1,"successRate":100,"tpCost":0,"tpGain":0},
{"animationId":0,"damage":{"critical":false,"elementId":0,"formula":"0","type":0,"variance":20},"description":"不管是惡魔還是神佛，都阻止不了我這慾望。","effects":[{"code":44,"dataId":109,"value1":1,"value2":0}],"hitType":0,"iconIndex":84,"id":45,"message1":"進行了%1！","message2":"","mpCost":0,"name":"性騷擾古菈布菈","note":"","occasion":1,"repeats":1,"requiredWtypeId1":0,"requiredWtypeId2":0,"scope":0,"speed":0,"stypeId":1,"successRate":100,"tpCost":0,"tpGain":0},
{"animationId":0,"damage":{"critical":false,"elementId":0,"formula":"9999","type":1,"variance":20},"description":"勇者使用的奧義。\n斬斷一切想要斬斷之物。還不到使用的時候。","effects":[{"code":44,"dataId":94,"value1":1,"value2":0}],"hitType":0,"iconIndex":97,"id":46,"message1":"釋放了%1！","message2":"以主人公的力量為代價，解放白劍的力量！！","mpCost":0,"name":"裂空劍","note":"","occasion":3,"repeats":1,"requiredWtypeId1":0,"requiredWtypeId2":0,"scope":1,"speed":0,"stypeId":1,"successRate":100,"tpCost":0,"tpGain":0},
{"animationId":0,"damage":{"critical":false,"elementId":0,"formula":"9999","type":1,"variance":20},"description":"勇者使用的奧義。\n斬斷一切想要斬斷之物。沒必要使用。","effects":[{"code":44,"dataId":94,"value1":1,"value2":0}],"hitType":0,"iconIndex":97,"id":47,"message1":"釋放了%1！","message2":"以主人公的力量為代價，解放白劍的力量！！","mpCost":0,"name":"裂空劍","note":"","occasion":3,"repeats":1,"requiredWtypeId1":0,"requiredWtypeId2":0,"scope":1,"speed":0,"stypeId":1,"successRate":100,"tpCost":0,"tpGain":0},
{"animationId":0,"damage":{"critical":false,"elementId":0,"formula":"0","type":0,"variance":20},"description":"","effects":[],"hitType":0,"iconIndex":0,"id":48,"message1":"","message2":"","mpCost":0,"name":"","note":"","occasion":0,"repeats":1,"requiredWtypeId1":0,"requiredWtypeId2":0,"scope":1,"speed":0,"stypeId":1,"successRate":100,"tpCost":0,"tpGain":0},
{"animationId":0,"damage":{"critical":false,"elementId":0,"formula":"0","type":0,"variance":20},"description":"","effects":[],"hitType":0,"iconIndex":0,"id":49,"message1":"","message2":"","mpCost":0,"name":"","note":"","occasion":0,"repeats":1,"requiredWtypeId1":0,"requiredWtypeId2":0,"scope":1,"speed":0,"stypeId":1,"successRate":100,"tpCost":0,"tpGain":0},
{"animationId":0,"damage":{"critical":false,"elementId":0,"formula":"0","type":0,"variance":20},"description":"","effects":[],"hitType":0,"iconIndex":0,"id":50,"message1":"","message2":"","mpCost":0,"name":"","note":"","occasion":0,"repeats":1,"requiredWtypeId1":0,"requiredWtypeId2":0,"scope":1,"speed":0,"stypeId":1,"successRate":100,"tpCost":0,"tpGain":0},
{"animationId":0,"damage":{"critical":false,"elementId":0,"formula":"0","type":0,"variance":20},"description":"讓海坂的好感度變成１。","effects":[{"code":44,"dataId":117,"value1":1,"value2":0}],"hitType":0,"iconIndex":25,"id":51,"message1":"","message2":"","mpCost":0,"name":"好感度變為１","note":"","occasion":2,"repeats":1,"requiredWtypeId1":0,"requiredWtypeId2":0,"scope":0,"speed":0,"stypeId":1,"successRate":100,"tpCost":0,"tpGain":0},
{"animationId":0,"damage":{"critical":false,"elementId":0,"formula":"0","type":0,"variance":20},"description":"讓海坂的好感度變成15。單相思。","effects":[{"code":44,"dataId":118,"value1":1,"value2":0}],"hitType":0,"iconIndex":25,"id":52,"message1":"","message2":"","mpCost":0,"name":"好感度變為15","note":"","occasion":2,"repeats":1,"requiredWtypeId1":0,"requiredWtypeId2":0,"scope":0,"speed":0,"stypeId":1,"successRate":100,"tpCost":0,"tpGain":0},
{"animationId":0,"damage":{"critical":false,"elementId":0,"formula":"0","type":0,"variance":20},"description":"好感度變為告白後。恩恩愛愛。","effects":[{"code":44,"dataId":119,"value1":1,"value2":0}],"hitType":0,"iconIndex":25,"id":53,"message1":"","message2":"","mpCost":0,"name":"好感度變為『告白後』","note":"","occasion":2,"repeats":1,"requiredWtypeId1":0,"requiredWtypeId2":0,"scope":0,"speed":0,"stypeId":1,"successRate":100,"tpCost":0,"tpGain":0},
{"animationId":0,"damage":{"critical":false,"elementId":0,"formula":"0","type":0,"variance":20},"description":"","effects":[],"hitType":0,"iconIndex":0,"id":54,"message1":"","message2":"","mpCost":0,"name":"","note":"","occasion":0,"repeats":1,"requiredWtypeId1":0,"requiredWtypeId2":0,"scope":1,"speed":0,"stypeId":1,"successRate":100,"tpCost":0,"tpGain":0},
{"animationId":0,"damage":{"critical":false,"elementId":0,"formula":"0","type":0,"variance":20},"description":"","effects":[],"hitType":0,"iconIndex":0,"id":55,"message1":"","message2":"","mpCost":0,"name":"","note":"","occasion":0,"repeats":1,"requiredWtypeId1":0,"requiredWtypeId2":0,"scope":1,"speed":0,"stypeId":1,"successRate":100,"tpCost":0,"tpGain":0},
{"animationId":0,"damage":{"critical":false,"elementId":0,"formula":"0","type":0,"variance":20},"description":"","effects":[],"hitType":0,"iconIndex":0,"id":56,"message1":"","message2":"","mpCost":0,"name":"","note":"","occasion":0,"repeats":1,"requiredWtypeId1":0,"requiredWtypeId2":0,"scope":1,"speed":0,"stypeId":1,"successRate":100,"tpCost":0,"tpGain":0},
{"animationId":0,"damage":{"critical":false,"elementId":0,"formula":"0","type":0,"variance":20},"description":"","effects":[],"hitType":0,"iconIndex":0,"id":57,"message1":"","message2":"","mpCost":0,"name":"","note":"","occasion":0,"repeats":1,"requiredWtypeId1":0,"requiredWtypeId2":0,"scope":1,"speed":0,"stypeId":1,"successRate":100,"tpCost":0,"tpGain":0},
{"animationId":0,"damage":{"critical":false,"elementId":0,"formula":"0","type":0,"variance":20},"description":"","effects":[],"hitType":0,"iconIndex":0,"id":58,"message1":"","message2":"","mpCost":0,"name":"","note":"","occasion":0,"repeats":1,"requiredWtypeId1":0,"requiredWtypeId2":0,"scope":1,"speed":0,"stypeId":1,"successRate":100,"tpCost":0,"tpGain":0},
{"animationId":0,"damage":{"critical":false,"elementId":0,"formula":"0","type":0,"variance":20},"description":"","effects":[],"hitType":0,"iconIndex":0,"id":59,"message1":"","message2":"","mpCost":0,"name":"","note":"","occasion":0,"repeats":1,"requiredWtypeId1":0,"requiredWtypeId2":0,"scope":1,"speed":0,"stypeId":1,"successRate":100,"tpCost":0,"tpGain":0},
{"animationId":0,"damage":{"critical":false,"elementId":0,"formula":"0","type":0,"variance":20},"description":"","effects":[],"hitType":0,"iconIndex":0,"id":60,"message1":"","message2":"","mpCost":0,"name":"","note":"","occasion":0,"repeats":1,"requiredWtypeId1":0,"requiredWtypeId2":0,"scope":1,"speed":0,"stypeId":1,"successRate":100,"tpCost":0,"tpGain":0},
{"animationId":0,"damage":{"critical":false,"elementId":0,"formula":"0","type":0,"variance":20},"description":"","effects":[],"hitType":0,"iconIndex":0,"id":61,"message1":"","message2":"","mpCost":0,"name":"","note":"","occasion":0,"repeats":1,"requiredWtypeId1":0,"requiredWtypeId2":0,"scope":1,"speed":0,"stypeId":1,"successRate":100,"tpCost":0,"tpGain":0},
{"animationId":0,"damage":{"critical":false,"elementId":0,"formula":"0","type":0,"variance":20},"description":"","effects":[],"hitType":0,"iconIndex":0,"id":62,"message1":"","message2":"","mpCost":0,"name":"","note":"","occasion":0,"repeats":1,"requiredWtypeId1":0,"requiredWtypeId2":0,"scope":1,"speed":0,"stypeId":1,"successRate":100,"tpCost":0,"tpGain":0},
{"animationId":0,"damage":{"critical":false,"elementId":0,"formula":"0","type":0,"variance":20},"description":"","effects":[],"hitType":0,"iconIndex":0,"id":63,"message1":"","message2":"","mpCost":0,"name":"","note":"","occasion":0,"repeats":1,"requiredWtypeId1":0,"requiredWtypeId2":0,"scope":1,"speed":0,"stypeId":1,"successRate":100,"tpCost":0,"tpGain":0},
{"animationId":0,"damage":{"critical":false,"elementId":0,"formula":"0","type":0,"variance":20},"description":"","effects":[],"hitType":0,"iconIndex":0,"id":64,"message1":"","message2":"","mpCost":0,"name":"","note":"","occasion":0,"repeats":1,"requiredWtypeId1":0,"requiredWtypeId2":0,"scope":1,"speed":0,"stypeId":1,"successRate":100,"tpCost":0,"tpGain":0},
{"animationId":0,"damage":{"critical":false,"elementId":0,"formula":"0","type":0,"variance":20},"description":"","effects":[],"hitType":0,"iconIndex":0,"id":65,"message1":"","message2":"","mpCost":0,"name":"","note":"","occasion":0,"repeats":1,"requiredWtypeId1":0,"requiredWtypeId2":0,"scope":1,"speed":0,"stypeId":1,"successRate":100,"tpCost":0,"tpGain":0},
{"animationId":0,"damage":{"critical":false,"elementId":0,"formula":"0","type":0,"variance":20},"description":"","effects":[],"hitType":0,"iconIndex":0,"id":66,"message1":"","message2":"","mpCost":0,"name":"","note":"","occasion":0,"repeats":1,"requiredWtypeId1":0,"requiredWtypeId2":0,"scope":1,"speed":0,"stypeId":1,"successRate":100,"tpCost":0,"tpGain":0},
{"animationId":0,"damage":{"critical":false,"elementId":0,"formula":"0","type":0,"variance":20},"description":"","effects":[],"hitType":0,"iconIndex":0,"id":67,"message1":"","message2":"","mpCost":0,"name":"","note":"","occasion":0,"repeats":1,"requiredWtypeId1":0,"requiredWtypeId2":0,"scope":1,"speed":0,"stypeId":1,"successRate":100,"tpCost":0,"tpGain":0},
{"animationId":0,"damage":{"critical":false,"elementId":0,"formula":"0","type":0,"variance":20},"description":"","effects":[],"hitType":0,"iconIndex":0,"id":68,"message1":"","message2":"","mpCost":0,"name":"","note":"","occasion":0,"repeats":1,"requiredWtypeId1":0,"requiredWtypeId2":0,"scope":1,"speed":0,"stypeId":1,"successRate":100,"tpCost":0,"tpGain":0},
{"animationId":0,"damage":{"critical":false,"elementId":0,"formula":"0","type":0,"variance":20},"description":"","effects":[],"hitType":0,"iconIndex":0,"id":69,"message1":"","message2":"","mpCost":0,"name":"","note":"","occasion":0,"repeats":1,"requiredWtypeId1":0,"requiredWtypeId2":0,"scope":1,"speed":0,"stypeId":1,"successRate":100,"tpCost":0,"tpGain":0},
{"animationId":0,"damage":{"critical":false,"elementId":0,"formula":"0","type":0,"variance":20},"description":"","effects":[],"hitType":0,"iconIndex":0,"id":70,"message1":"","message2":"","mpCost":0,"name":"","note":"","occasion":0,"repeats":1,"requiredWtypeId1":0,"requiredWtypeId2":0,"scope":1,"speed":0,"stypeId":1,"successRate":100,"tpCost":0,"tpGain":0},
{"animationId":0,"damage":{"critical":false,"elementId":0,"formula":"0","type":0,"variance":20},"description":"","effects":[],"hitType":0,"iconIndex":0,"id":71,"message1":"","message2":"","mpCost":0,"name":"","note":"","occasion":0,"repeats":1,"requiredWtypeId1":0,"requiredWtypeId2":0,"scope":1,"speed":0,"stypeId":1,"successRate":100,"tpCost":0,"tpGain":0},
{"animationId":0,"damage":{"critical":false,"elementId":0,"formula":"0","type":0,"variance":20},"description":"","effects":[],"hitType":0,"iconIndex":0,"id":72,"message1":"","message2":"","mpCost":0,"name":"","note":"","occasion":0,"repeats":1,"requiredWtypeId1":0,"requiredWtypeId2":0,"scope":1,"speed":0,"stypeId":1,"successRate":100,"tpCost":0,"tpGain":0},
{"animationId":0,"damage":{"critical":false,"elementId":0,"formula":"0","type":0,"variance":20},"description":"","effects":[],"hitType":0,"iconIndex":0,"id":73,"message1":"","message2":"","mpCost":0,"name":"","note":"","occasion":0,"repeats":1,"requiredWtypeId1":0,"requiredWtypeId2":0,"scope":1,"speed":0,"stypeId":1,"successRate":100,"tpCost":0,"tpGain":0},
{"animationId":0,"damage":{"critical":false,"elementId":0,"formula":"0","type":0,"variance":20},"description":"","effects":[],"hitType":0,"iconIndex":0,"id":74,"message1":"","message2":"","mpCost":0,"name":"","note":"","occasion":0,"repeats":1,"requiredWtypeId1":0,"requiredWtypeId2":0,"scope":1,"speed":0,"stypeId":1,"successRate":100,"tpCost":0,"tpGain":0},
{"animationId":0,"damage":{"critical":false,"elementId":0,"formula":"0","type":0,"variance":20},"description":"","effects":[],"hitType":0,"iconIndex":0,"id":75,"message1":"","message2":"","mpCost":0,"name":"","note":"","occasion":0,"repeats":1,"requiredWtypeId1":0,"requiredWtypeId2":0,"scope":1,"speed":0,"stypeId":1,"successRate":100,"tpCost":0,"tpGain":0},
{"animationId":0,"damage":{"critical":false,"elementId":0,"formula":"0","type":0,"variance":20},"description":"","effects":[],"hitType":0,"iconIndex":0,"id":76,"message1":"","message2":"","mpCost":0,"name":"","note":"","occasion":0,"repeats":1,"requiredWtypeId1":0,"requiredWtypeId2":0,"scope":1,"speed":0,"stypeId":1,"successRate":100,"tpCost":0,"tpGain":0},
{"animationId":0,"damage":{"critical":false,"elementId":0,"formula":"0","type":0,"variance":20},"description":"","effects":[],"hitType":0,"iconIndex":0,"id":77,"message1":"","message2":"","mpCost":0,"name":"","note":"","occasion":0,"repeats":1,"requiredWtypeId1":0,"requiredWtypeId2":0,"scope":1,"speed":0,"stypeId":1,"successRate":100,"tpCost":0,"tpGain":0},
{"animationId":0,"damage":{"critical":false,"elementId":0,"formula":"0","type":0,"variance":20},"description":"","effects":[],"hitType":0,"iconIndex":0,"id":78,"message1":"","message2":"","mpCost":0,"name":"","note":"","occasion":0,"repeats":1,"requiredWtypeId1":0,"requiredWtypeId2":0,"scope":1,"speed":0,"stypeId":1,"successRate":100,"tpCost":0,"tpGain":0},
{"animationId":0,"damage":{"critical":false,"elementId":0,"formula":"0","type":0,"variance":20},"description":"","effects":[],"hitType":0,"iconIndex":0,"id":79,"message1":"","message2":"","mpCost":0,"name":"","note":"","occasion":0,"repeats":1,"requiredWtypeId1":0,"requiredWtypeId2":0,"scope":1,"speed":0,"stypeId":1,"successRate":100,"tpCost":0,"tpGain":0},
{"animationId":0,"damage":{"critical":false,"elementId":0,"formula":"0","type":0,"variance":20},"description":"","effects":[],"hitType":0,"iconIndex":0,"id":80,"message1":"","message2":"","mpCost":0,"name":"","note":"","occasion":0,"repeats":1,"requiredWtypeId1":0,"requiredWtypeId2":0,"scope":1,"speed":0,"stypeId":1,"successRate":100,"tpCost":0,"tpGain":0},
{"animationId":0,"damage":{"critical":false,"elementId":0,"formula":"0","type":0,"variance":20},"description":"","effects":[],"hitType":0,"iconIndex":0,"id":81,"message1":"","message2":"","mpCost":0,"name":"","note":"","occasion":0,"repeats":1,"requiredWtypeId1":0,"requiredWtypeId2":0,"scope":1,"speed":0,"stypeId":1,"successRate":100,"tpCost":0,"tpGain":0},
{"animationId":0,"damage":{"critical":false,"elementId":0,"formula":"0","type":0,"variance":20},"description":"","effects":[],"hitType":0,"iconIndex":0,"id":82,"message1":"","message2":"","mpCost":0,"name":"","note":"","occasion":0,"repeats":1,"requiredWtypeId1":0,"requiredWtypeId2":0,"scope":1,"speed":0,"stypeId":1,"successRate":100,"tpCost":0,"tpGain":0},
{"animationId":0,"damage":{"critical":false,"elementId":0,"formula":"0","type":0,"variance":20},"description":"","effects":[],"hitType":0,"iconIndex":0,"id":83,"message1":"","message2":"","mpCost":0,"name":"","note":"","occasion":0,"repeats":1,"requiredWtypeId1":0,"requiredWtypeId2":0,"scope":1,"speed":0,"stypeId":1,"successRate":100,"tpCost":0,"tpGain":0},
{"animationId":0,"damage":{"critical":false,"elementId":0,"formula":"0","type":0,"variance":20},"description":"","effects":[],"hitType":0,"iconIndex":0,"id":84,"message1":"","message2":"","mpCost":0,"name":"","note":"","occasion":0,"repeats":1,"requiredWtypeId1":0,"requiredWtypeId2":0,"scope":1,"speed":0,"stypeId":1,"successRate":100,"tpCost":0,"tpGain":0},
{"animationId":0,"damage":{"critical":false,"elementId":0,"formula":"0","type":0,"variance":20},"description":"","effects":[],"hitType":0,"iconIndex":0,"id":85,"message1":"","message2":"","mpCost":0,"name":"","note":"","occasion":0,"repeats":1,"requiredWtypeId1":0,"requiredWtypeId2":0,"scope":1,"speed":0,"stypeId":1,"successRate":100,"tpCost":0,"tpGain":0},
{"animationId":0,"damage":{"critical":false,"elementId":0,"formula":"0","type":0,"variance":20},"description":"","effects":[],"hitType":0,"iconIndex":0,"id":86,"message1":"","message2":"","mpCost":0,"name":"","note":"","occasion":0,"repeats":1,"requiredWtypeId1":0,"requiredWtypeId2":0,"scope":1,"speed":0,"stypeId":1,"successRate":100,"tpCost":0,"tpGain":0},
{"animationId":0,"damage":{"critical":false,"elementId":0,"formula":"0","type":0,"variance":20},"description":"","effects":[],"hitType":0,"iconIndex":0,"id":87,"message1":"","message2":"","mpCost":0,"name":"","note":"","occasion":0,"repeats":1,"requiredWtypeId1":0,"requiredWtypeId2":0,"scope":1,"speed":0,"stypeId":1,"successRate":100,"tpCost":0,"tpGain":0},
{"animationId":0,"damage":{"critical":false,"elementId":0,"formula":"0","type":0,"variance":20},"description":"","effects":[],"hitType":0,"iconIndex":0,"id":88,"message1":"","message2":"","mpCost":0,"name":"","note":"","occasion":0,"repeats":1,"requiredWtypeId1":0,"requiredWtypeId2":0,"scope":1,"speed":0,"stypeId":1,"successRate":100,"tpCost":0,"tpGain":0},
{"animationId":0,"damage":{"critical":false,"elementId":0,"formula":"0","type":0,"variance":20},"description":"","effects":[],"hitType":0,"iconIndex":0,"id":89,"message1":"","message2":"","mpCost":0,"name":"","note":"","occasion":0,"repeats":1,"requiredWtypeId1":0,"requiredWtypeId2":0,"scope":1,"speed":0,"stypeId":1,"successRate":100,"tpCost":0,"tpGain":0},
{"animationId":0,"damage":{"critical":false,"elementId":0,"formula":"0","type":0,"variance":20},"description":"","effects":[],"hitType":0,"iconIndex":0,"id":90,"message1":"","message2":"","mpCost":0,"name":"","note":"","occasion":0,"repeats":1,"requiredWtypeId1":0,"requiredWtypeId2":0,"scope":1,"speed":0,"stypeId":1,"successRate":100,"tpCost":0,"tpGain":0},
{"animationId":0,"damage":{"critical":false,"elementId":0,"formula":"0","type":0,"variance":20},"description":"","effects":[],"hitType":0,"iconIndex":0,"id":91,"message1":"","message2":"","mpCost":0,"name":"","note":"","occasion":0,"repeats":1,"requiredWtypeId1":0,"requiredWtypeId2":0,"scope":1,"speed":0,"stypeId":1,"successRate":100,"tpCost":0,"tpGain":0},
{"animationId":0,"damage":{"critical":false,"elementId":0,"formula":"0","type":0,"variance":20},"description":"","effects":[],"hitType":0,"iconIndex":0,"id":92,"message1":"","message2":"","mpCost":0,"name":"","note":"","occasion":0,"repeats":1,"requiredWtypeId1":0,"requiredWtypeId2":0,"scope":1,"speed":0,"stypeId":1,"successRate":100,"tpCost":0,"tpGain":0},
{"animationId":0,"damage":{"critical":false,"elementId":0,"formula":"0","type":0,"variance":20},"description":"","effects":[],"hitType":0,"iconIndex":0,"id":93,"message1":"","message2":"","mpCost":0,"name":"","note":"","occasion":0,"repeats":1,"requiredWtypeId1":0,"requiredWtypeId2":0,"scope":1,"speed":0,"stypeId":1,"successRate":100,"tpCost":0,"tpGain":0},
{"animationId":0,"damage":{"critical":false,"elementId":0,"formula":"0","type":0,"variance":20},"description":"","effects":[],"hitType":0,"iconIndex":0,"id":94,"message1":"","message2":"","mpCost":0,"name":"","note":"","occasion":0,"repeats":1,"requiredWtypeId1":0,"requiredWtypeId2":0,"scope":1,"speed":0,"stypeId":1,"successRate":100,"tpCost":0,"tpGain":0},
{"animationId":0,"damage":{"critical":false,"elementId":0,"formula":"0","type":0,"variance":20},"description":"","effects":[],"hitType":0,"iconIndex":0,"id":95,"message1":"","message2":"","mpCost":0,"name":"","note":"","occasion":0,"repeats":1,"requiredWtypeId1":0,"requiredWtypeId2":0,"scope":1,"speed":0,"stypeId":1,"successRate":100,"tpCost":0,"tpGain":0},
{"animationId":0,"damage":{"critical":false,"elementId":0,"formula":"0","type":0,"variance":20},"description":"","effects":[],"hitType":0,"iconIndex":0,"id":96,"message1":"","message2":"","mpCost":0,"name":"","note":"","occasion":0,"repeats":1,"requiredWtypeId1":0,"requiredWtypeId2":0,"scope":1,"speed":0,"stypeId":1,"successRate":100,"tpCost":0,"tpGain":0},
{"animationId":0,"damage":{"critical":false,"elementId":0,"formula":"0","type":0,"variance":20},"description":"","effects":[],"hitType":0,"iconIndex":0,"id":97,"message1":"","message2":"","mpCost":0,"name":"","note":"","occasion":0,"repeats":1,"requiredWtypeId1":0,"requiredWtypeId2":0,"scope":1,"speed":0,"stypeId":1,"successRate":100,"tpCost":0,"tpGain":0},
{"animationId":0,"damage":{"critical":false,"elementId":0,"formula":"0","type":0,"variance":20},"description":"","effects":[],"hitType":0,"iconIndex":0,"id":98,"message1":"","message2":"","mpCost":0,"name":"","note":"","occasion":0,"repeats":1,"requiredWtypeId1":0,"requiredWtypeId2":0,"scope":1,"speed":0,"stypeId":1,"successRate":100,"tpCost":0,"tpGain":0},
{"animationId":0,"damage":{"critical":false,"elementId":0,"formula":"0","type":0,"variance":20},"description":"","effects":[],"hitType":0,"iconIndex":0,"id":99,"message1":"","message2":"","mpCost":0,"name":"","note":"","occasion":0,"repeats":1,"requiredWtypeId1":0,"requiredWtypeId2":0,"scope":1,"speed":0,"stypeId":1,"successRate":100,"tpCost":0,"tpGain":0}
]